{
  "Object": "PricebookEntry",
  "Fields": {
    "GearsetDisplayName": "Standard Price Book - SSD Hard Drive 128GB",
    "GearsetExternalId__c": "YAAFF1u200000mbu10",
    "IsActive": "true",
    "UnitPrice": "50.0",
    "UseStandardPrice": "false"
  },
  "References": [
    {
      "Name": "Pricebook2",
      "ReferencedObject": "Pricebook2",
      "ReferencedFields": {
        "GearsetExternalId__c": "StandardPriceBook"
      }
    },
    {
      "Name": "Product2",
      "ReferencedObject": "Product2",
      "ReferencedFields": {
        "GearsetExternalId__c": "3AAGRV2B00000mbt10"
      }
    }
  ]
}